{
  "annotations": {
    "list": [
      {
        "builtIn": 1,
        "datasource": {
          "type": "grafana",
          "uid": "-- Grafana --"
        },
        "enable": true,
        "hide": true,
        "iconColor": "rgba(0, 211, 255, 1)",
        "name": "Annotations & Alerts",
        "type": "dashboard"
      }
    ]
  },
  "editable": true,
  "fiscalYearStartMonth": 0,
  "graphTooltip": 0,
  "links": [],
  "liveNow": false,
  "panels": [
    {
      "datasource": {
        "type": "influxdb",
        "uid": "e6f8ad70-fa53-4820-8449-3c51a7f39693"
      },
      "fieldConfig": {
        "defaults": {
          "color": {
            "mode": "palette-classic"
          },
          "custom": {
            "axisBorderShow": false,
            "axisCenteredZero": false,
            "axisColorMode": "text",
            "axisLabel": "",
            "axisPlacement": "auto",
            "barAlignment": 0,
            "drawStyle": "line",
            "fillOpacity": 0,
            "gradientMode": "none",
            "hideFrom": {
              "legend": false,
              "tooltip": false,
              "viz": false
            },
            "insertNulls": false,
            "lineInterpolation": "linear",
            "lineWidth": 1,
            "pointSize": 5,
            "scaleDistribution": {
              "type": "linear"
            },
            "showPoints": "auto",
            "spanNulls": false,
            "stacking": {
              "group": "A",
              "mode": "none"
            },
            "thresholdsStyle": {
              "mode": "off"
            }
          },
          "mappings": [],
          "thresholds": {
            "mode": "absolute",
            "steps": [
              {
                "color": "green",
                "value": null
              },
              {
                "color": "red",
                "value": 80
              }
            ]
          }
        },
        "overrides": []
      },
      "gridPos": {
        "h": 5,
        "w": 8,
        "x": 0,
        "y": 0
      },
      "id": 11,
      "options": {
        "legend": {
          "calcs": [],
          "displayMode": "list",
          "placement": "bottom",
          "showLegend": true
        },
        "tooltip": {
          "mode": "single",
          "sort": "none"
        }
      },
      "targets": [
        {
          "alias": "Cloudflare",
          "datasource": {
            "type": "influxdb",
            "uid": "e6f8ad70-fa53-4820-8449-3c51a7f39693"
          },
          "groupBy": [
            {
              "params": [
                "1s"
              ],
              "type": "time"
            },
            {
              "params": [
                "null"
              ],
              "type": "fill"
            }
          ],
          "hide": false,
          "measurement": "rtt",
          "orderByTime": "DESC",
          "policy": "default",
          "refId": "Cloudflare",
          "resultFormat": "time_series",
          "select": [
            [
              {
                "params": [
                  "rtt"
                ],
                "type": "field"
              },
              {
                "params": [],
                "type": "first"
              }
            ]
          ],
          "tags": [
            {
              "key": "dst::tag",
              "operator": "=",
              "value": "1.1.1.1"
            }
          ]
        },
        {
          "alias": "Google",
          "datasource": {
            "type": "influxdb",
            "uid": "e6f8ad70-fa53-4820-8449-3c51a7f39693"
          },
          "groupBy": [
            {
              "params": [
                "1s"
              ],
              "type": "time"
            },
            {
              "params": [
                "null"
              ],
              "type": "fill"
            }
          ],
          "hide": false,
          "measurement": "rtt",
          "orderByTime": "DESC",
          "policy": "default",
          "refId": "B",
          "resultFormat": "time_series",
          "select": [
            [
              {
                "params": [
                  "rtt"
                ],
                "type": "field"
              },
              {
                "params": [],
                "type": "first"
              }
            ]
          ],
          "tags": [
            {
              "key": "dst::tag",
              "operator": "=",
              "value": "8.8.8.8"
            }
          ]
        }
      ],
      "title": "Pinger",
      "type": "timeseries"
    },
    {
      "datasource": {
        "type": "prometheus",
        "uid": "ff0f8d29-bd9d-46b5-9338-5a50a114eb0a"
      },
      "description": "",
      "fieldConfig": {
        "defaults": {
          "mappings": [
            {
              "options": {
                "0": {
                  "index": 1,
                  "text": "DOWN"
                },
                "1": {
                  "index": 0,
                  "text": "UP"
                }
              },
              "type": "value"
            }
          ],
          "thresholds": {
            "mode": "absolute",
            "steps": [
              {
                "color": "green",
                "value": null
              },
              {
                "color": "red",
                "value": 0
              },
              {
                "color": "dark-green",
                "value": 1
              }
            ]
          },
          "unit": "short"
        },
        "overrides": []
      },
      "gridPos": {
        "h": 3,
        "w": 4,
        "x": 8,
        "y": 0
      },
      "id": 3,
      "options": {
        "colorMode": "background",
        "graphMode": "none",
        "justifyMode": "auto",
        "orientation": "auto",
        "reduceOptions": {
          "calcs": [
            "lastNotNull"
          ],
          "fields": "",
          "values": false
        },
        "textMode": "auto",
        "wideLayout": true
      },
      "pluginVersion": "10.2.2",
      "targets": [
        {
          "datasource": {
            "type": "prometheus",
            "uid": "ff0f8d29-bd9d-46b5-9338-5a50a114eb0a"
          },
          "disableTextWrap": false,
          "editorMode": "builder",
          "expr": "bind_up",
          "fullMetaSearch": false,
          "includeNullMetadata": true,
          "instant": false,
          "legendFormat": "__auto",
          "range": true,
          "refId": "A",
          "useBackend": false
        }
      ],
      "title": "Bind9",
      "type": "stat"
    },
    {
      "datasource": {
        "type": "prometheus",
        "uid": "ff0f8d29-bd9d-46b5-9338-5a50a114eb0a"
      },
      "description": "",
      "fieldConfig": {
        "defaults": {
          "mappings": [
            {
              "options": {
                "0": {
                  "index": 1,
                  "text": "DOWN"
                },
                "1": {
                  "index": 0,
                  "text": "UP"
                }
              },
              "type": "value"
            }
          ],
          "thresholds": {
            "mode": "absolute",
            "steps": [
              {
                "color": "green",
                "value": null
              },
              {
                "color": "red",
                "value": 0
              },
              {
                "color": "dark-green",
                "value": 1
              }
            ]
          },
          "unit": "short"
        },
        "overrides": []
      },
      "gridPos": {
        "h": 3,
        "w": 4,
        "x": 12,
        "y": 0
      },
      "id": 12,
      "options": {
        "colorMode": "background",
        "graphMode": "none",
        "justifyMode": "auto",
        "orientation": "auto",
        "reduceOptions": {
          "calcs": [
            "lastNotNull"
          ],
          "fields": "",
          "values": false
        },
        "textMode": "auto",
        "wideLayout": true
      },
      "pluginVersion": "10.2.2",
      "targets": [
        {
          "datasource": {
            "type": "prometheus",
            "uid": "ff0f8d29-bd9d-46b5-9338-5a50a114eb0a"
          },
          "disableTextWrap": false,
          "editorMode": "builder",
          "expr": "influxdb_exporter_stats_query_success",
          "fullMetaSearch": false,
          "includeNullMetadata": true,
          "instant": false,
          "legendFormat": "__auto",
          "range": true,
          "refId": "A",
          "useBackend": false
        }
      ],
      "title": "InfluxDB",
      "type": "stat"
    },
    {
      "datasource": {
        "type": "prometheus",
        "uid": "ff0f8d29-bd9d-46b5-9338-5a50a114eb0a"
      },
      "description": "",
      "fieldConfig": {
        "defaults": {
          "mappings": [
            {
              "options": {
                "0": {
                  "index": 1,
                  "text": "DOWN"
                },
                "1": {
                  "index": 0,
                  "text": "UP"
                }
              },
              "type": "value"
            }
          ],
          "thresholds": {
            "mode": "absolute",
            "steps": [
              {
                "color": "green",
                "value": null
              },
              {
                "color": "red",
                "value": 0
              },
              {
                "color": "dark-green",
                "value": 1
              }
            ]
          },
          "unit": "short"
        },
        "overrides": []
      },
      "gridPos": {
        "h": 3,
        "w": 8,
        "x": 16,
        "y": 0
      },
      "id": 2,
      "options": {
        "colorMode": "background",
        "graphMode": "none",
        "justifyMode": "auto",
        "orientation": "auto",
        "reduceOptions": {
          "calcs": [
            "lastNotNull"
          ],
          "fields": "",
          "values": false
        },
        "textMode": "auto",
        "wideLayout": true
      },
      "pluginVersion": "10.2.2",
      "targets": [
        {
          "datasource": {
            "type": "prometheus",
            "uid": "ff0f8d29-bd9d-46b5-9338-5a50a114eb0a"
          },
          "disableTextWrap": false,
          "editorMode": "builder",
          "expr": "nginx_up",
          "fullMetaSearch": false,
          "includeNullMetadata": true,
          "instant": false,
          "legendFormat": "{{instance}}",
          "range": true,
          "refId": "A",
          "useBackend": false
        }
      ],
      "title": "Nginx",
      "type": "stat"
    },
    {
      "datasource": {
        "type": "prometheus",
        "uid": "ff0f8d29-bd9d-46b5-9338-5a50a114eb0a"
      },
      "fieldConfig": {
        "defaults": {
          "color": {
            "mode": "thresholds"
          },
          "mappings": [],
          "thresholds": {
            "mode": "absolute",
            "steps": [
              {
                "color": "green",
                "value": null
              },
              {
                "color": "red",
                "value": 80
              }
            ]
          }
        },
        "overrides": [
          {
            "matcher": {
              "id": "byName",
              "options": "{instance=\"pavroto-2:9119\", job=\"DNS\", type=\"A\", view=\"_default\"}"
            },
            "properties": [
              {
                "id": "displayName",
                "value": "A Type"
              }
            ]
          },
          {
            "matcher": {
              "id": "byName",
              "options": "{instance=\"pavroto-2:9119\", job=\"DNS\", type=\"AAAA\", view=\"_default\"}"
            },
            "properties": [
              {
                "id": "displayName",
                "value": "AAAA Type"
              }
            ]
          },
          {
            "matcher": {
              "id": "byName",
              "options": "{instance=\"pavroto-2:9119\", job=\"DNS\", type=\"MX\", view=\"_default\"}"
            },
            "properties": [
              {
                "id": "displayName",
                "value": "MX Type"
              }
            ]
          },
          {
            "matcher": {
              "id": "byName",
              "options": "{instance=\"pavroto-2:9119\", job=\"DNS\", type=\"NS\", view=\"_default\"}"
            },
            "properties": [
              {
                "id": "displayName",
                "value": "NS Type"
              }
            ]
          },
          {
            "matcher": {
              "id": "byName",
              "options": "{instance=\"pavroto-2:9119\", job=\"DNS\", type=\"SRV\", view=\"_default\"}"
            },
            "properties": [
              {
                "id": "displayName",
                "value": "SRV Type"
              }
            ]
          }
        ]
      },
      "gridPos": {
        "h": 19,
        "w": 4,
        "x": 8,
        "y": 3
      },
      "id": 8,
      "options": {
        "colorMode": "value",
        "graphMode": "area",
        "justifyMode": "auto",
        "orientation": "auto",
        "reduceOptions": {
          "calcs": [
            "lastNotNull"
          ],
          "fields": "",
          "values": false
        },
        "textMode": "auto",
        "wideLayout": true
      },
      "pluginVersion": "10.2.2",
      "targets": [
        {
          "datasource": {
            "type": "prometheus",
            "uid": "ff0f8d29-bd9d-46b5-9338-5a50a114eb0a"
          },
          "editorMode": "builder",
          "expr": "rate(bind_resolver_queries_total[1m])*60",
          "instant": false,
          "legendFormat": "__auto",
          "range": true,
          "refId": "A"
        }
      ],
      "title": "DNS queries",
      "type": "stat"
    },
    {
      "datasource": {
        "type": "prometheus",
        "uid": "ff0f8d29-bd9d-46b5-9338-5a50a114eb0a"
      },
      "fieldConfig": {
        "defaults": {
          "color": {
            "mode": "thresholds"
          },
          "mappings": [],
          "thresholds": {
            "mode": "absolute",
            "steps": [
              {
                "color": "green",
                "value": null
              },
              {
                "color": "red",
                "value": 80
              }
            ]
          }
        },
        "overrides": []
      },
      "gridPos": {
        "h": 5,
        "w": 4,
        "x": 12,
        "y": 3
      },
      "id": 13,
      "options": {
        "colorMode": "value",
        "graphMode": "area",
        "justifyMode": "auto",
        "orientation": "auto",
        "reduceOptions": {
          "calcs": [
            "lastNotNull"
          ],
          "fields": "",
          "values": false
        },
        "textMode": "auto",
        "wideLayout": true
      },
      "pluginVersion": "10.2.2",
      "targets": [
        {
          "datasource": {
            "type": "prometheus",
            "uid": "ff0f8d29-bd9d-46b5-9338-5a50a114eb0a"
          },
          "disableTextWrap": false,
          "editorMode": "code",
          "expr": "sum(rate(influxdb_write_write_ok[1m]))",
          "fullMetaSearch": false,
          "includeNullMetadata": false,
          "instant": false,
          "legendFormat": "__auto",
          "range": true,
          "refId": "A",
          "useBackend": false
        }
      ],
      "title": "InfluxDB write rate",
      "type": "stat"
    },
    {
      "datasource": {
        "type": "prometheus",
        "uid": "ff0f8d29-bd9d-46b5-9338-5a50a114eb0a"
      },
      "fieldConfig": {
        "defaults": {
          "color": {
            "mode": "thresholds"
          },
          "mappings": [],
          "thresholds": {
            "mode": "absolute",
            "steps": [
              {
                "color": "green",
                "value": null
              },
              {
                "color": "red",
                "value": 80
              }
            ]
          }
        },
        "overrides": []
      },
      "gridPos": {
        "h": 5,
        "w": 8,
        "x": 16,
        "y": 3
      },
      "id": 10,
      "options": {
        "colorMode": "value",
        "graphMode": "area",
        "justifyMode": "auto",
        "orientation": "auto",
        "reduceOptions": {
          "calcs": [
            "lastNotNull"
          ],
          "fields": "",
          "values": false
        },
        "textMode": "auto",
        "wideLayout": true
      },
      "pluginVersion": "10.2.2",
      "targets": [
        {
          "datasource": {
            "type": "prometheus",
            "uid": "ff0f8d29-bd9d-46b5-9338-5a50a114eb0a"
          },
          "disableTextWrap": false,
          "editorMode": "code",
          "expr": "sum(rate(nginx_http_requests_total[1m]))",
          "fullMetaSearch": false,
          "includeNullMetadata": false,
          "instant": false,
          "legendFormat": "__auto",
          "range": true,
          "refId": "A",
          "useBackend": false
        }
      ],
      "title": "Nginx requests",
      "type": "stat"
    },
    {
      "datasource": {
        "type": "prometheus",
        "uid": "ff0f8d29-bd9d-46b5-9338-5a50a114eb0a"
      },
      "fieldConfig": {
        "defaults": {
          "color": {
            "mode": "palette-classic"
          },
          "custom": {
            "axisBorderShow": false,
            "axisCenteredZero": false,
            "axisColorMode": "text",
            "axisLabel": "",
            "axisPlacement": "auto",
            "barAlignment": 0,
            "drawStyle": "line",
            "fillOpacity": 0,
            "gradientMode": "none",
            "hideFrom": {
              "legend": false,
              "tooltip": false,
              "viz": false
            },
            "insertNulls": false,
            "lineInterpolation": "linear",
            "lineWidth": 1,
            "pointSize": 5,
            "scaleDistribution": {
              "type": "linear"
            },
            "showPoints": "auto",
            "spanNulls": false,
            "stacking": {
              "group": "A",
              "mode": "none"
            },
            "thresholdsStyle": {
              "mode": "off"
            }
          },
          "mappings": [],
          "thresholds": {
            "mode": "absolute",
            "steps": [
              {
                "color": "green",
                "value": null
              },
              {
                "color": "red",
                "value": 80
              }
            ]
          }
        },
        "overrides": [
          {
            "matcher": {
              "id": "byName",
              "options": " 100 - (avg(rate(node_cpu_seconds_total{mode=\"idle\", instance=\"pavroto-1:9100\"}[5m])) * 100)"
            },
            "properties": [
              {
                "id": "displayName",
                "value": "CPU"
              }
            ]
          }
        ]
      },
      "gridPos": {
        "h": 6,
        "w": 4,
        "x": 0,
        "y": 5
      },
      "id": 4,
      "options": {
        "legend": {
          "calcs": [],
          "displayMode": "list",
          "placement": "bottom",
          "showLegend": true
        },
        "tooltip": {
          "mode": "single",
          "sort": "none"
        }
      },
      "targets": [
        {
          "datasource": {
            "type": "prometheus",
            "uid": "ff0f8d29-bd9d-46b5-9338-5a50a114eb0a"
          },
          "disableTextWrap": false,
          "editorMode": "code",
          "expr": " 100 - (avg(rate(node_cpu_seconds_total{mode=\"idle\", instance=\"pavroto-1:9100\"}[5m])) * 100)",
          "fullMetaSearch": false,
          "includeNullMetadata": true,
          "instant": false,
          "legendFormat": "__auto",
          "range": true,
          "refId": "A",
          "useBackend": false
        }
      ],
      "title": "pavroto-1 CPU",
      "type": "timeseries"
    },
    {
      "datasource": {
        "type": "prometheus",
        "uid": "ff0f8d29-bd9d-46b5-9338-5a50a114eb0a"
      },
      "fieldConfig": {
        "defaults": {
          "color": {
            "mode": "palette-classic"
          },
          "custom": {
            "axisBorderShow": false,
            "axisCenteredZero": false,
            "axisColorMode": "text",
            "axisLabel": "",
            "axisPlacement": "auto",
            "barAlignment": 0,
            "drawStyle": "line",
            "fillOpacity": 0,
            "gradientMode": "none",
            "hideFrom": {
              "legend": false,
              "tooltip": false,
              "viz": false
            },
            "insertNulls": false,
            "lineInterpolation": "linear",
            "lineWidth": 1,
            "pointSize": 5,
            "scaleDistribution": {
              "type": "linear"
            },
            "showPoints": "auto",
            "spanNulls": false,
            "stacking": {
              "group": "A",
              "mode": "none"
            },
            "thresholdsStyle": {
              "mode": "off"
            }
          },
          "mappings": [],
          "thresholds": {
            "mode": "absolute",
            "steps": [
              {
                "color": "green",
                "value": null
              },
              {
                "color": "red",
                "value": 80
              }
            ]
          }
        },
        "overrides": [
          {
            "matcher": {
              "id": "byName",
              "options": "{instance=\"pavroto-1:9100\", job=\"linux\"}"
            },
            "properties": [
              {
                "id": "displayName",
                "value": "RAM"
              }
            ]
          }
        ]
      },
      "gridPos": {
        "h": 6,
        "w": 4,
        "x": 4,
        "y": 5
      },
      "id": 6,
      "options": {
        "legend": {
          "calcs": [],
          "displayMode": "list",
          "placement": "bottom",
          "showLegend": true
        },
        "tooltip": {
          "mode": "single",
          "sort": "none"
        }
      },
      "targets": [
        {
          "datasource": {
            "type": "prometheus",
            "uid": "ff0f8d29-bd9d-46b5-9338-5a50a114eb0a"
          },
          "editorMode": "code",
          "expr": " (1 - (node_memory_MemFree_bytes{instance=\"pavroto-1:9100\"} + node_memory_Cached_bytes{instance=\"pavroto-1:9100\"} + node_memory_Buffers_bytes{instance=\"pavroto-1:9100\"}) / node_memory_MemTotal_bytes{instance=\"pavroto-1:9100\"}) * 100",
          "instant": false,
          "legendFormat": "__auto",
          "range": true,
          "refId": "A"
        }
      ],
      "title": "pavroto-1 RAM",
      "type": "timeseries"
    },
    {
      "datasource": {
        "type": "prometheus",
        "uid": "ff0f8d29-bd9d-46b5-9338-5a50a114eb0a"
      },
      "description": "",
      "fieldConfig": {
        "defaults": {
          "mappings": [
            {
              "options": {
                "0": {
                  "index": 1,
                  "text": "DOWN"
                },
                "1": {
                  "index": 0,
                  "text": "UP"
                }
              },
              "type": "value"
            }
          ],
          "thresholds": {
            "mode": "absolute",
            "steps": [
              {
                "color": "green",
                "value": null
              },
              {
                "color": "red",
                "value": 0
              },
              {
                "color": "dark-green",
                "value": 1
              }
            ]
          },
          "unit": "short"
        },
        "overrides": []
      },
      "gridPos": {
        "h": 3,
        "w": 12,
        "x": 12,
        "y": 8
      },
      "id": 15,
      "options": {
        "colorMode": "background",
        "graphMode": "none",
        "justifyMode": "auto",
        "orientation": "auto",
        "reduceOptions": {
          "calcs": [
            "lastNotNull"
          ],
          "fields": "",
          "values": false
        },
        "textMode": "auto",
        "wideLayout": true
      },
      "pluginVersion": "10.2.2",
      "targets": [
        {
          "datasource": {
            "type": "prometheus",
            "uid": "ff0f8d29-bd9d-46b5-9338-5a50a114eb0a"
          },
          "disableTextWrap": false,
          "editorMode": "builder",
          "expr": "haproxy_up",
          "fullMetaSearch": false,
          "includeNullMetadata": true,
          "instant": false,
          "legendFormat": "{{instance}}",
          "range": true,
          "refId": "A",
          "useBackend": false
        }
      ],
      "title": "HAProxy",
      "type": "stat"
    },
    {
      "datasource": {
        "type": "prometheus",
        "uid": "ff0f8d29-bd9d-46b5-9338-5a50a114eb0a"
      },
      "fieldConfig": {
        "defaults": {
          "color": {
            "mode": "palette-classic"
          },
          "custom": {
            "axisBorderShow": false,
            "axisCenteredZero": false,
            "axisColorMode": "text",
            "axisLabel": "",
            "axisPlacement": "auto",
            "barAlignment": 0,
            "drawStyle": "line",
            "fillOpacity": 0,
            "gradientMode": "none",
            "hideFrom": {
              "legend": false,
              "tooltip": false,
              "viz": false
            },
            "insertNulls": false,
            "lineInterpolation": "linear",
            "lineWidth": 1,
            "pointSize": 5,
            "scaleDistribution": {
              "type": "linear"
            },
            "showPoints": "auto",
            "spanNulls": false,
            "stacking": {
              "group": "A",
              "mode": "none"
            },
            "thresholdsStyle": {
              "mode": "off"
            }
          },
          "mappings": [],
          "thresholds": {
            "mode": "absolute",
            "steps": [
              {
                "color": "green",
                "value": null
              },
              {
                "color": "red",
                "value": 80
              }
            ]
          }
        },
        "overrides": [
          {
            "matcher": {
              "id": "byName",
              "options": " 100 - (avg(rate(node_cpu_seconds_total{mode=\"idle\", instance=\"pavroto-2:9100\"}[5m])) * 100)"
            },
            "properties": [
              {
                "id": "displayName",
                "value": "CPU"
              }
            ]
          }
        ]
      },
      "gridPos": {
        "h": 6,
        "w": 4,
        "x": 0,
        "y": 11
      },
      "id": 5,
      "options": {
        "legend": {
          "calcs": [],
          "displayMode": "list",
          "placement": "bottom",
          "showLegend": true
        },
        "tooltip": {
          "mode": "single",
          "sort": "none"
        }
      },
      "targets": [
        {
          "datasource": {
            "type": "prometheus",
            "uid": "ff0f8d29-bd9d-46b5-9338-5a50a114eb0a"
          },
          "disableTextWrap": false,
          "editorMode": "code",
          "expr": " 100 - (avg(rate(node_cpu_seconds_total{mode=\"idle\", instance=\"pavroto-2:9100\"}[5m])) * 100)",
          "fullMetaSearch": false,
          "includeNullMetadata": true,
          "instant": false,
          "legendFormat": "__auto",
          "range": true,
          "refId": "A",
          "useBackend": false
        }
      ],
      "title": "pavroto-2 CPU",
      "type": "timeseries"
    },
    {
      "datasource": {
        "type": "prometheus",
        "uid": "ff0f8d29-bd9d-46b5-9338-5a50a114eb0a"
      },
      "fieldConfig": {
        "defaults": {
          "color": {
            "mode": "palette-classic"
          },
          "custom": {
            "axisBorderShow": false,
            "axisCenteredZero": false,
            "axisColorMode": "text",
            "axisLabel": "",
            "axisPlacement": "auto",
            "barAlignment": 0,
            "drawStyle": "line",
            "fillOpacity": 0,
            "gradientMode": "none",
            "hideFrom": {
              "legend": false,
              "tooltip": false,
              "viz": false
            },
            "insertNulls": false,
            "lineInterpolation": "linear",
            "lineWidth": 1,
            "pointSize": 5,
            "scaleDistribution": {
              "type": "linear"
            },
            "showPoints": "auto",
            "spanNulls": false,
            "stacking": {
              "group": "A",
              "mode": "none"
            },
            "thresholdsStyle": {
              "mode": "off"
            }
          },
          "mappings": [],
          "thresholds": {
            "mode": "absolute",
            "steps": [
              {
                "color": "green",
                "value": null
              },
              {
                "color": "red",
                "value": 80
              }
            ]
          }
        },
        "overrides": [
          {
            "matcher": {
              "id": "byName",
              "options": "{instance=\"pavroto-2:9100\", job=\"linux\"}"
            },
            "properties": [
              {
                "id": "displayName",
                "value": "RAM"
              }
            ]
          }
        ]
      },
      "gridPos": {
        "h": 6,
        "w": 4,
        "x": 4,
        "y": 11
      },
      "id": 7,
      "options": {
        "legend": {
          "calcs": [],
          "displayMode": "list",
          "placement": "bottom",
          "showLegend": true
        },
        "tooltip": {
          "mode": "single",
          "sort": "none"
        }
      },
      "targets": [
        {
          "datasource": {
            "type": "prometheus",
            "uid": "ff0f8d29-bd9d-46b5-9338-5a50a114eb0a"
          },
          "editorMode": "code",
          "expr": " (1 - (node_memory_MemFree_bytes{instance=\"pavroto-2:9100\"} + node_memory_Cached_bytes{instance=\"pavroto-2:9100\"} + node_memory_Buffers_bytes{instance=\"pavroto-2:9100\"}) / node_memory_MemTotal_bytes{instance=\"pavroto-2:9100\"}) * 100",
          "instant": false,
          "legendFormat": "__auto",
          "range": true,
          "refId": "A"
        }
      ],
      "title": "pavroto-2 RAM",
      "type": "timeseries"
    },
    {
      "datasource": {
        "type": "prometheus",
        "uid": "ff0f8d29-bd9d-46b5-9338-5a50a114eb0a"
      },
      "description": "",
      "fieldConfig": {
        "defaults": {
          "mappings": [
            {
              "options": {
                "0": {
                  "index": 1,
                  "text": "DOWN"
                },
                "1": {
                  "index": 0,
                  "text": "UP"
                }
              },
              "type": "value"
            }
          ],
          "thresholds": {
            "mode": "absolute",
            "steps": [
              {
                "color": "green",
                "value": null
              },
              {
                "color": "red",
                "value": 0
              },
              {
                "color": "dark-green",
                "value": 1
              }
            ]
          },
          "unit": "short"
        },
        "overrides": []
      },
      "gridPos": {
        "h": 3,
        "w": 12,
        "x": 12,
        "y": 11
      },
      "id": 16,
      "options": {
        "colorMode": "background",
        "graphMode": "none",
        "justifyMode": "auto",
        "orientation": "auto",
        "reduceOptions": {
          "calcs": [
            "lastNotNull"
          ],
          "fields": "",
          "values": false
        },
        "textMode": "auto",
        "wideLayout": true
      },
      "pluginVersion": "10.2.2",
      "targets": [
        {
          "datasource": {
            "type": "prometheus",
            "uid": "ff0f8d29-bd9d-46b5-9338-5a50a114eb0a"
          },
          "disableTextWrap": false,
          "editorMode": "builder",
          "expr": "haproxy_server_up",
          "fullMetaSearch": false,
          "includeNullMetadata": true,
          "instant": false,
          "legendFormat": "{{instance}} {{server}}",
          "range": true,
          "refId": "A",
          "useBackend": false
        }
      ],
      "title": "HAProxy Servers",
      "type": "stat"
    },
    {
      "datasource": {
        "type": "prometheus",
        "uid": "ff0f8d29-bd9d-46b5-9338-5a50a114eb0a"
      },
      "fieldConfig": {
        "defaults": {
          "color": {
            "mode": "thresholds"
          },
          "mappings": [],
          "thresholds": {
            "mode": "absolute",
            "steps": [
              {
                "color": "green",
                "value": null
              },
              {
                "color": "red",
                "value": 80
              }
            ]
          }
        },
        "overrides": []
      },
      "gridPos": {
        "h": 8,
        "w": 12,
        "x": 12,
        "y": 14
      },
      "id": 17,
      "options": {
        "minVizHeight": 75,
        "minVizWidth": 75,
        "orientation": "auto",
        "reduceOptions": {
          "calcs": [
            "lastNotNull"
          ],
          "fields": "",
          "values": false
        },
        "showThresholdLabels": false,
        "showThresholdMarkers": true
      },
      "pluginVersion": "10.2.2",
      "targets": [
        {
          "datasource": {
            "type": "prometheus",
            "uid": "ff0f8d29-bd9d-46b5-9338-5a50a114eb0a"
          },
          "disableTextWrap": false,
          "editorMode": "builder",
          "expr": "keepalived_vrrp_state",
          "fullMetaSearch": false,
          "includeNullMetadata": true,
          "instant": false,
          "legendFormat": "{{instance}}",
          "range": true,
          "refId": "A",
          "useBackend": false
        }
      ],
      "title": "Keepalived State",
      "type": "gauge"
    }
  ],
  "refresh": "5s",
  "schemaVersion": 38,
  "tags": [],
  "templating": {
    "list": []
  },
  "time": {
    "from": "now-5m",
    "to": "now"
  },
  "timepicker": {},
  "timezone": "",
  "title": "ica0002",
  "uid": "b48dd164-d14f-4905-bd10-c05b148924ee",
  "version": 1,
  "weekStart": ""
}
